pymywork/__init__.py
pymywork/mywork.py
pymywork-0.0.1.dist-info/LICENSE
pymywork-0.0.1.dist-info/METADATA
pymywork-0.0.1.dist-info/WHEEL
pymywork-0.0.1.dist-info/top_level.txt
pymywork-0.0.1.dist-info/RECORD
